xia_compiler_jsoneditor/__init__.py
xia_compiler_jsoneditor/compiler.cp311-win_amd64.pyd
xia_compiler_jsoneditor-0.1.7.dist-info/LICENSE.txt
xia_compiler_jsoneditor-0.1.7.dist-info/METADATA
xia_compiler_jsoneditor-0.1.7.dist-info/WHEEL
xia_compiler_jsoneditor-0.1.7.dist-info/top_level.txt
xia_compiler_jsoneditor-0.1.7.dist-info/RECORD
