Metadata-Version: 2.1
Name: xia-compiler-jsoneditor
Version: 0.1.7
Home-page: https://develop.x-i-a.com/docs/xia-compiler-jsoneditor/0.1.7/index.html
Author: X-I-A
Author-email: admin@x-i-a.com
Requires-Python: >=3.9
License-File: LICENSE.txt
Requires-Dist: xia-api
